kubectlgetall/__init__.py
kubectlgetall/cli.py
kubectlgetall-0.3.0.dist-info/METADATA
kubectlgetall-0.3.0.dist-info/WHEEL
kubectlgetall-0.3.0.dist-info/entry_points.txt
kubectlgetall-0.3.0.dist-info/RECORD
